setup.py
demo/__init__.py
spriter/__init__.py
spriter/sprite.py
spriter/spriter_watcher.py
spriter.egg-info/PKG-INFO
spriter.egg-info/SOURCES.txt
spriter.egg-info/dependency_links.txt
spriter.egg-info/requires.txt
spriter.egg-info/top_level.txt
spriter/image/__init__.py
tests/__init__.py
tests/test_base64_sprites.py
tests/test_base_image.py
tests/test_default_image.py
tests/test_gen_image.py
tests/test_images.py
tests/test_optimization.py
tests/test_watcher.py