Metadata-Version: 1.1
Name: spriter
Version: 1.2
Summary: Pitomba's sprite generator
Home-page: http://pitomba.org
Author: Rômulo Jales
Author-email: romulo@romulojales.com
License: Apache License 2.0
Download-URL: https://github.com/pitomba/pitomba
Keywords: pitomba sprite css images generator png webp
Platform: UNKNOWN
Classifier: Development Status :: 5 - Production/Stable
Classifier: Intended Audience :: Developers
Classifier: Programming Language :: Python
